README.md
setup.py
shortbred_identify.py
shortbred_quantify.py
shortbred.egg-info/PKG-INFO
shortbred.egg-info/SOURCES.txt
shortbred.egg-info/dependency_links.txt
shortbred.egg-info/not-zip-safe
shortbred.egg-info/requires.txt
shortbred.egg-info/top_level.txt
shortbred_src/__init__.py
shortbred_src/check_sequences.py
shortbred_src/check_windows.py
shortbred_src/fastq2fasta.py
shortbred_src/make_windows.py
shortbred_src/process_blast.py
shortbred_src/quantify_functions.py