Metadata-Version: 1.1
Name: shortbred
Version: 0.9.5
Summary: ShortBRED: a system for profiling protein families of interest at very high specificity in shotgun meta’omic sequencing data
Home-page: http://huttenhower.sph.harvard.edu/shortbred
Author: Shortbred Development Team
Author-email: shortbred-users@googlegroups.com
License: MIT
Keywords: microbial,microbiome,bioinformatics,microbiology,metagenomic,shortbred
Platform: Linux
Platform: MacOS
Classifier: Programming Language :: Python
Classifier: Development Status :: 5 - Production/Stable
Classifier: Environment :: Console
Classifier: Operating System :: MacOS
Classifier: Operating System :: Unix
Classifier: Programming Language :: Python :: 3.4
Classifier: Topic :: Scientific/Engineering :: Bio-Informatics
